minchin.pelican.themes.minchindotca-1.1.0-py3.5-nspkg.pth
minchin/pelican/themes/minchindotca/__init__.py
minchin/pelican/themes/minchindotca/static/css/bootstrap-theme.css
minchin/pelican/themes/minchindotca/static/css/bootstrap-theme.min.css
minchin/pelican/themes/minchindotca/static/css/bootstrap.amelia.min.css
minchin/pelican/themes/minchindotca/static/css/bootstrap.cerulean.min.css
minchin/pelican/themes/minchindotca/static/css/bootstrap.cosmo.min.css
minchin/pelican/themes/minchindotca/static/css/bootstrap.css
minchin/pelican/themes/minchindotca/static/css/bootstrap.cupid.min.css
minchin/pelican/themes/minchindotca/static/css/bootstrap.cyborg.min.css
minchin/pelican/themes/minchindotca/static/css/bootstrap.darkly.min.css
minchin/pelican/themes/minchindotca/static/css/bootstrap.flatly.min.css
minchin/pelican/themes/minchindotca/static/css/bootstrap.journal.min.css
minchin/pelican/themes/minchindotca/static/css/bootstrap.lumen.min.css
minchin/pelican/themes/minchindotca/static/css/bootstrap.min.css
minchin/pelican/themes/minchindotca/static/css/bootstrap.minchindotca.min.css
minchin/pelican/themes/minchindotca/static/css/bootstrap.paper.min.css
minchin/pelican/themes/minchindotca/static/css/bootstrap.readable-old.min.css
minchin/pelican/themes/minchindotca/static/css/bootstrap.readable.min.css
minchin/pelican/themes/minchindotca/static/css/bootstrap.sandstone.min.css
minchin/pelican/themes/minchindotca/static/css/bootstrap.shamrock.min.css
minchin/pelican/themes/minchindotca/static/css/bootstrap.simplex.min.css
minchin/pelican/themes/minchindotca/static/css/bootstrap.slate.min.css
minchin/pelican/themes/minchindotca/static/css/bootstrap.spacelab.min.css
minchin/pelican/themes/minchindotca/static/css/bootstrap.superhero.min.css
minchin/pelican/themes/minchindotca/static/css/bootstrap.united.min.css
minchin/pelican/themes/minchindotca/static/css/bootstrap.yeti.min.css
minchin/pelican/themes/minchindotca/static/css/font-awesome.css
minchin.pelican.themes.minchindotca-1.1.0.dist-info/DESCRIPTION.rst
minchin.pelican.themes.minchindotca-1.1.0.dist-info/METADATA
minchin.pelican.themes.minchindotca-1.1.0.dist-info/RECORD
minchin.pelican.themes.minchindotca-1.1.0.dist-info/WHEEL
minchin.pelican.themes.minchindotca-1.1.0.dist-info/metadata.json
minchin.pelican.themes.minchindotca-1.1.0.dist-info/namespace_packages.txt
minchin.pelican.themes.minchindotca-1.1.0.dist-info/top_level.txt
