Metadata-Version: 2.0
Name: minchin.pelican.themes.minchindotca
Version: 1.1.0
Summary: Pelican theme, first used for Minchin.ca.
Home-page: https://github.com/MinchinWeb/minchin.pelican.themes.minchindotca
Author: W. Minchin
Author-email: w_minchin@hotmail.com
License: UNKNOWN
Platform: UNKNOWN
Classifier: Development Status :: 5 - Production/Stable
Classifier: Environment :: Console
Classifier: License :: OSI Approved :: MIT License
Classifier: Programming Language :: Python
Classifier: Programming Language :: Python :: 3
Classifier: Programming Language :: Python :: 3.4
Classifier: Programming Language :: Python :: 3.5
Classifier: Topic :: Multimedia :: Graphics
Classifier: Topic :: Software Development :: Libraries :: Python Modules
Requires-Dist: minchin.pelican.plugins.image-process (>=1.0.1)
Requires-Dist: pelican
